{
  "generator-jhipster": {
    "applicationType": "monolith",
    "gitCompany": "",
    "baseName": "xinghaokfApplication",
    "packageName": "com.xiaohao.kf",
    "packageFolder": "com/xiaohao/kf",
    "serverPort": 8080,
    "serviceDiscoveryType": false,
    "authenticationType": "jwt",
    "uaaBaseName": "../uaa",
    "cacheProvider": "hazelcast",
    "enableHibernateCache": true,
    "websocket": "spring-websocket",
    "databaseType": "sql",
    "devDatabaseType": "mysql",
    "prodDatabaseType": "mysql",
    "searchEngine": "elasticsearch",
    "enableSwaggerCodegen": "true",
    "messageBroker": "kafka",
    "buildTool": "maven",
    "useSass": true,
    "clientPackageManager": "npm",
    "testFrameworks": ["gatling", "cucumber", "protractor"],
    "enableTranslation": false,
    "nativeLanguage": "zh-cn",
    "languages": ["zh-cn"],
    "clientFramework": "react",
    "jhiPrefix": "jhi",
    "jhipsterVersion": "6.10.5",
    "jwtSecretKey": "N2U0M2YwMTY5ZGUyMzZjNmRhNWQ2ZWZlZTdjYWRlZGM4ZTAyN2ExNjg5NTdiNzk5ODhjNWQ2N2E1MzI2NjAxMjljYjNjODVkYWE1ZjhkYWU4M2YxYzI4ZThhYWY0YmVhMjczZGU3OGM4YmQ4N2UwYmEzZGM3MjNiM2JhNmI4ODY=",
    "embeddableLaunchScript": false,
    "clientTheme": "none",
    "creationTimestamp": 1609853181216,
    "entitySuffix": "",
    "dtoSuffix": "DTO",
    "otherModules": [],
    "blueprints": [],
    "prettierJava": true
  },
  "git-provider": "GitHub",
  "git-company": "googlezhang",
  "repository-name": "xiaohao-kf-application"
}
